starlette_login/__init__.py
starlette_login/backends.py
starlette_login/decorator.py
starlette_login/login_manager.py
starlette_login/middleware.py
starlette_login/mixins.py
starlette_login/utils.py
starlette_login-1.0.3.dist-info/licenses/LICENSE
starlette_login-1.0.3.dist-info/METADATA
starlette_login-1.0.3.dist-info/WHEEL
starlette_login-1.0.3.dist-info/top_level.txt
starlette_login-1.0.3.dist-info/RECORD
